<?xml version="1.0" encoding="UTF-8" standalone="yes" ?>

#######################################################################################################################################
<item>
<title>[COLOR orange] Must Have Plexus Addon Installed[/COLOR]</title>
<link>.</link>
<thumbnail></thumbnail>
</item>
#######################################################################################################################################

<item>
<title>Sky Sports 1</title>
<link>plugin://program.plexus/?mode=1&url=acestream://b57aeaf809d32442e9585753aa8d2420b6481f8e&name=Sky+Sports+1</link>
<thumbnail>http://i376.photobucket.com/albums/oo204/indiecrew/SukanTV/skysports_zpsi1xgekaj.png</thumbnail>
</item>

<item>
<title>Sky Sports 3</title>
<link>plugin://program.plexus/?mode=1&url=acestream://4dbce55abecd154ff71b3477a332bd63611309e5&name=Sky+Sports+3</link>
<thumbnail>http://i376.photobucket.com/albums/oo204/indiecrew/SukanTV/skysports_zpsi1xgekaj.png</thumbnail>
</item>

<item>
<title>Sky Sports 4</title>
<link>plugin://program.plexus/?mode=1&url=acestream://11e5b8dcc1ff06c7fa5071ce4718bcc5f867d668&name=Sky+Sports+4</link>
<thumbnail>http://i376.photobucket.com/albums/oo204/indiecrew/SukanTV/skysports_zpsi1xgekaj.png</thumbnail>
</item>
